LICENSE.txt
README.md
pyproject.toml
aleph/__init__.py
aleph/py.typed
aleph/sdk/__init__.py
aleph/sdk/account.py
aleph/sdk/conf.py
aleph/sdk/domain.py
aleph/sdk/evm_utils.py
aleph/sdk/exceptions.py
aleph/sdk/types.py
aleph/sdk/utils.py
aleph/sdk/chains/__init__.py
aleph/sdk/chains/common.py
aleph/sdk/chains/cosmos.py
aleph/sdk/chains/ethereum.py
aleph/sdk/chains/evm.py
aleph/sdk/chains/nuls1.py
aleph/sdk/chains/nuls2.py
aleph/sdk/chains/remote.py
aleph/sdk/chains/sol.py
aleph/sdk/chains/solana.py
aleph/sdk/chains/substrate.py
aleph/sdk/chains/svm.py
aleph/sdk/chains/tezos.py
aleph/sdk/client/__init__.py
aleph/sdk/client/abstract.py
aleph/sdk/client/authenticated_http.py
aleph/sdk/client/http.py
aleph/sdk/client/vm_client.py
aleph/sdk/client/vm_confidential_client.py
aleph/sdk/client/services/__init__.py
aleph/sdk/client/services/authenticated_port_forwarder.py
aleph/sdk/client/services/authenticated_voucher.py
aleph/sdk/client/services/base.py
aleph/sdk/client/services/crn.py
aleph/sdk/client/services/dns.py
aleph/sdk/client/services/instance.py
aleph/sdk/client/services/port_forwarder.py
aleph/sdk/client/services/pricing.py
aleph/sdk/client/services/scheduler.py
aleph/sdk/client/services/settings.py
aleph/sdk/client/services/voucher.py
aleph/sdk/connectors/superfluid.py
aleph/sdk/query/filters.py
aleph/sdk/query/responses.py
aleph/sdk/vm/__init__.py
aleph/sdk/vm/app.py
aleph/sdk/vm/cache.py
aleph/sdk/wallets/__init__.py
aleph/sdk/wallets/ledger/__init__.py
aleph/sdk/wallets/ledger/ethereum.py
aleph_sdk_python-2.3.0.dist-info/METADATA
aleph_sdk_python-2.3.0.dist-info/WHEEL
aleph_sdk_python-2.3.0.dist-info/licenses/AUTHORS.rst
aleph_sdk_python-2.3.0.dist-info/licenses/LICENSE.txt
aleph_sdk_python-2.3.0.dist-info/RECORD
