Metadata-Version: 2.4
Name: aleph-sdk-python
Version: 2.3.0
Summary: Lightweight Python Client library for the Aleph.im network
Project-URL: Documentation, https://aleph.im/
Project-URL: Homepage, https://github.com/aleph-im/aleph-sdk-python
Author-email: "Aleph.im Team" <hello@aleph.im>
License: The MIT License (MIT)
License-File: AUTHORS.rst
License-File: LICENSE.txt
Classifier: Development Status :: 4 - Beta
Classifier: Framework :: aiohttp
Classifier: Intended Audience :: Developers
Classifier: License :: OSI Approved :: MIT License
Classifier: Operating System :: MacOS :: MacOS X
Classifier: Operating System :: POSIX :: Linux
Classifier: Programming Language :: Python :: 3 :: Only
Classifier: Programming Language :: Python :: 3.8
Classifier: Programming Language :: Python :: 3.9
Classifier: Programming Language :: Python :: 3.10
Classifier: Programming Language :: Python :: 3.11
Classifier: Programming Language :: Python :: 3.12
Classifier: Topic :: Software Development :: Libraries
Requires-Dist: aiohttp>=3.8.3
Requires-Dist: aioresponses>=0.7.6
Requires-Dist: aleph-message>=1.0.5
Requires-Dist: aleph-superfluid>=0.3
Requires-Dist: base58==2.1.1
Requires-Dist: coincurve; python_version >= '3.9'
Requires-Dist: coincurve>=19; python_version >= '3.9'
Requires-Dist: eth-abi>=5.0.1; python_version >= '3.9'
Requires-Dist: eth-typing>=5.0.1
Requires-Dist: jwcrypto==1.5.6
Requires-Dist: ledgerblue>=0.1.48
Requires-Dist: ledgereth>=0.10
Requires-Dist: pydantic-settings>=2
Requires-Dist: pydantic<3,>=2
Requires-Dist: pynacl==1.5
Requires-Dist: python-magic
Requires-Dist: typing-extensions
Requires-Dist: web3>=7.10
Provides-Extra: all
Requires-Dist: aiodns; extra == 'all'
Requires-Dist: aiomqtt<=0.1.3; extra == 'all'
Requires-Dist: aleph-nuls2; extra == 'all'
Requires-Dist: base58; extra == 'all'
Requires-Dist: certifi; extra == 'all'
Requires-Dist: click; extra == 'all'
Requires-Dist: cosmospy; extra == 'all'
Requires-Dist: eciespy; (python_version < '3.11') and extra == 'all'
Requires-Dist: eciespy>=0.3.13; (python_version >= '3.11') and extra == 'all'
Requires-Dist: ledgereth==0.10; extra == 'all'
Requires-Dist: py-sr25519-bindings; extra == 'all'
Requires-Dist: pynacl; extra == 'all'
Requires-Dist: pytezos-crypto==3.13.4.1; extra == 'all'
Requires-Dist: sphinxcontrib-plantuml; extra == 'all'
Requires-Dist: substrate-interface<1.8; extra == 'all'
Provides-Extra: cosmos
Requires-Dist: cosmospy; extra == 'cosmos'
Provides-Extra: dns
Requires-Dist: aiodns; extra == 'dns'
Provides-Extra: docs
Requires-Dist: sphinxcontrib-plantuml; extra == 'docs'
Provides-Extra: encryption
Requires-Dist: eciespy; (python_version < '3.11') and extra == 'encryption'
Requires-Dist: eciespy>=0.3.13; (python_version >= '3.11') and extra == 'encryption'
Provides-Extra: ledger
Requires-Dist: ledgereth==0.10; extra == 'ledger'
Provides-Extra: mqtt
Requires-Dist: aiomqtt<=0.1.3; extra == 'mqtt'
Requires-Dist: certifi; extra == 'mqtt'
Requires-Dist: click; extra == 'mqtt'
Provides-Extra: nuls2
Requires-Dist: aleph-nuls2; extra == 'nuls2'
Provides-Extra: solana
Requires-Dist: base58; extra == 'solana'
Requires-Dist: pynacl; extra == 'solana'
Provides-Extra: substrate
Requires-Dist: py-sr25519-bindings; extra == 'substrate'
Requires-Dist: substrate-interface<1.8; extra == 'substrate'
Provides-Extra: tezos
Requires-Dist: pytezos-crypto==3.13.4.1; extra == 'tezos'
